v_pvmismatch/__init__.py
v_pvmismatch/cell_curr.py
v_pvmismatch/circuit_comb.py
v_pvmismatch/plotting.py
v_pvmismatch/utils.py
v_pvmismatch/version.py
v_pvmismatch/vpvcell.py
v_pvmismatch/vpvmodule.py
v_pvmismatch/vpvstring.py
v_pvmismatch/vpvsystem.py
v_pvmismatch/pvmismatch/__init__.py
v_pvmismatch/pvmismatch/pvcell.py
v_pvmismatch/pvmismatch/pvconstants.py
v_pvmismatch/pvmismatch/pvexceptions.py
v_pvmismatch/pvmismatch/pvmodule.py
v_pvmismatch/pvmismatch/pvstring.py
v_pvmismatch/pvmismatch/pvsystem.py
v_pvmismatch-0.2.4.dist-info/licenses/LICENSE
v_pvmismatch-0.2.4.dist-info/METADATA
v_pvmismatch-0.2.4.dist-info/WHEEL
v_pvmismatch-0.2.4.dist-info/top_level.txt
v_pvmismatch-0.2.4.dist-info/RECORD
