Metadata-Version: 2.4
Name: v_pvmismatch
Version: 0.2.4
Summary: Vectorized PVMismatch (v_PVMismatch) Package.
Author-email: Kiran Balasubramanian <kiran.balasubramanian@maxeon.com>
Maintainer-email: Kiran Balasubramanian <kiran.balasubramanian@maxeon.com>
Project-URL: Homepage, https://github.com/Maxeon-RnD/v_pvmismatch
Project-URL: Issues, https://github.com/Maxeon-RnD/v_pvmismatch/issues
Keywords: pvmismatch,PV,shading,mismatch,IV
Classifier: Programming Language :: Python :: 3
Classifier: License :: OSI Approved :: MIT License
Classifier: Operating System :: OS Independent
License-File: LICENSE
Requires-Dist: matplotlib
Requires-Dist: plotly
Requires-Dist: future
Requires-Dist: numpy
Requires-Dist: scipy
Dynamic: license-file
